.DS_Store
drf_tracking_extended-1.2.1.dist-info/DESCRIPTION.rst
drf_tracking_extended-1.2.1.dist-info/METADATA
drf_tracking_extended-1.2.1.dist-info/RECORD
drf_tracking_extended-1.2.1.dist-info/WHEEL
drf_tracking_extended-1.2.1.dist-info/metadata.json
drf_tracking_extended-1.2.1.dist-info/top_level.txt
rest_framework_tracking/.DS_Store
rest_framework_tracking/__init__.py
rest_framework_tracking/admin.py
rest_framework_tracking/apps.py
rest_framework_tracking/managers.py
rest_framework_tracking/mixins.py
rest_framework_tracking/models.py
rest_framework_tracking/migrations/.DS_Store
rest_framework_tracking/migrations/0001_initial.py
rest_framework_tracking/migrations/__init__.py
