Metadata-Version: 2.0
Name: drf-tracking-extended
Version: 1.2.1
Summary: Utils to log Django Rest Framework requests to the database. Fork of drf-tracking with extended features.
Home-page: https://github.com/frankie567/drf-tracking
Author: François Voron
Author-email: fvoron@gmail.com
License: ISC
Platform: UNKNOWN
Classifier: Development Status :: 2 - Pre-Alpha
Classifier: Environment :: Web Environment
Classifier: Framework :: Django
Classifier: Framework :: Django :: 1.7
Classifier: Framework :: Django :: 1.8
Classifier: Framework :: Django :: 1.9
Classifier: Framework :: Django :: 1.10
Classifier: Intended Audience :: Developers
Classifier: Operating System :: OS Independent
Classifier: Natural Language :: English
Classifier: Programming Language :: Python :: 2
Classifier: Programming Language :: Python :: 2.7
Classifier: Programming Language :: Python :: 3
Classifier: Programming Language :: Python :: 3.3
Classifier: Programming Language :: Python :: 3.4
Classifier: Programming Language :: Python :: 3.5
Classifier: Topic :: Internet :: WWW/HTTP
Requires-Dist: Django (>=1.7)
Requires-Dist: djangorestframework (>=3)
Requires-Dist: pytz
